<?xml version="1.0" standalone="no" ?>
<!DOCTYPE pov SYSTEM "/usr/share/cgc-docs/replay.dtd">
<pov>
	<cbid>CROMU_00025</cbid>
	<replay>
		<read echo="ascii"><delim>} </delim><match><data>1- Upload Image\n2- List Images\n3- Remove Image\n4- Display Image\n5- Leave\n} </data></match></read>
		<write echo="ascii"><data>1\n</data></write>
		<read echo="ascii"><delim>: </delim><match><data>Image Name: </data></match></read>
		<write echo="ascii"><data>tkaaozbqc\n</data></write>
		<write echo="ascii"><data>\x23\x00\xd3\x09\x51\xc3\x91\x43\x02\xd8\x90\x00\x50\x28\x33\x29\x8c\x83\x34\x49\x32\xa0\x00\x49\xaa\x10\x9c\xc8\x80\x28\x8a\x04\x18\x3c\x58\x50\xc0</data></write>
		<read echo="ascii"><delim>} </delim><match><data>1- Upload Image\n2- List Images\n3- Remove Image\n4- Display Image\n5- Leave\n} </data></match></read>
		<write echo="ascii"><data>1\n</data></write>
		<read echo="ascii"><delim>: </delim><match><data>Image Name: </data></match></read>
		<write echo="ascii"><data>uxpzi\n</data></write>
		<write echo="ascii"><data>\x11\x00\x24\xc7\xee\x85\x70\xf1\x80\x00\x2a\x1c\xd8\x71\xe0\xc5\x0b\x2a\x18</data></write>
		<read echo="ascii"><delim>} </delim><match><data>1- Upload Image\n2- List Images\n3- Remove Image\n4- Display Image\n5- Leave\n} </data></match></read>
		<write echo="ascii"><data>1\n</data></write>
		<read echo="ascii"><delim>: </delim><match><data>Image Name: </data></match></read>
		<write echo="ascii"><data>kwlpsvnpykuovu\n</data></write>
		<write echo="ascii"><data>\xda\x01\xcb\x59\x0f\x31\x45\xf4\x00\x00\x11\x69\x48\xa7\x90\x27\xdb\xb2\x9c\x4a\x72\x01\x61\x03\x43\x10\x5a\x65\x2a\xe8\x8d\x5a\xba\xdb\xca\x23\xd8\x4f\xab\x65\x7b\x29\xb4\x4a\xae\x0a\x38\x59\x99\xe3\x6e\x19\x8a\x92\x14\x64\xab\xca\x52\x5f\x34\x64\x85\x55\xa4\x10\x22\xd6\xcd\x95\x05\xc9\x9b\x06\x0c\x95\x09\xd2\xd7\xcf\x30\xc0\xfd\x5a\x89\x5d\x0a\x14\x14\x94\xab\x17\xdd\x16\x42\xc0\xec\x77\xd3\xc4\x96\x9d\x49\x61\x6b\x89\x2c\xaa\x64\xcc\x92\xe3\x61\x52\x0d\x0b\x5a\x7a\xd4\x6f\xec\x43\x90\xc1\x7a\x45\x25\xe3\x99\x5c\x22\x81\xc0\x63\x8d\xc8\x5b\x09\xb1\x19\x6c\x44\x41\xae\x66\x9c\x83\xe0\x55\xbd\x24\x34\xcd\x12\x68\x66\x36\x62\x20\x51\x66\x2f\x87\x57\x48\xde\x9d\xf1\xe6\xcf\xc7\xa8\x82\x11\xb2\x8b\x03\x25\x22\xb0\x2a\x48\xf6\x51\xd8\xba\x54\xc1\xe8\xc7\x43\x2f\xa4\x72\xbb\xd6\xae\x4c\x09\x3a\xf2\x59\xaa\x66\x5a\x46\x79\x46\xfb\x52\x25\x49\x2f\x1a\xfa\x24\x28\xc2\xe5\x28\x4c\xf9\xc1\x17\x0e\xd1\x5e\x60\xa2\x48\xb2\xf7\x22\x8e\x14\x66\xa1\x09\xad\x25\x30\x1d\x10\x5c\x05\x0a\x26\x08\x6c\xb2\x1b\xe5\x56\xc9\x4a\x74\x86\x7c\x70\xe5\xaf\x99\xb9\x55\x6b\x13\xd4\x6e\xd2\x1e\x75\x42\xd7\x89\xe4\x41\x22\xd4\xaa\x83\x37\xc9\xdd\xa0\xe1\xa4\x62\xca\xd6\x49\x30\xc4\xad\x07\x8b\x5d\xba\x20\x85\xfd\x57\x0e\x5e\x41\x41\x3a\x22\xe4\xcf\x55\x8f\x4c\xde\xf4\x53\x30\x6b\x3e\x24\x91\x04\x4b\xf3\x53\xcc\x0e\xbd\xbb\x30\xe8\x5e\x86\x95\x09\x13\x09\x23\xe4\x28\x41\x26\x89\xf7\xae\xc0\x9c\x8c\xf1\x5b\xe5\x03\x99\x2e\x17\x48\x14\xe8\x4a\x9f\x5e\x36\x80\x12\x27\xac\x82\x2e\x71\x31\x31\x3b\x12\xab\x3c\x38\x91\x68\x15\xb5\xa8\x40\x6c\x21\x73\x82\xe5\xeb\xbc\x71\x31\x58\x12\xae\x65\x3a\xa7\x7e\x11\xb5\x07\x69\x3b\x54\x8d\x7d\xc8\xce\x0a\x40\x0e\x29\xea\xda\xf1\x89\xbf\x82\x9e\x02\xc3\x09\x1b\x44\x86\x6e\x38\x3a\x63\x1e\x54\x88\xc1\xf4\x3b\xa6\xef\xb4\x79\x78\xb2\xa2\x23\x6a\x3f\x5a\x18\xe2\xb0\x68\x9c\x11\x58\x6e\xd8\xb3\xe7\x98\x4a\x8d\x0a\x43\x57\x4d\x16\x8f\x10\x6c\xfd\x80\xec\xe6\x80\x00\x00\xad\x97</data></write>
		<read echo="ascii"><delim>} </delim><match><data>1- Upload Image\n2- List Images\n3- Remove Image\n4- Display Image\n5- Leave\n} </data></match></read>
		<write echo="ascii"><data>1\n</data></write>
		<read echo="ascii"><delim>: </delim><match><data>Image Name: </data></match></read>
		<write echo="ascii"><data>llnwvyhbgxyi\n</data></write>
		<write echo="ascii"><data>\x46\x00\xde\xb6\xd9\x55\x3d\x0f\x08\x88\x88\x0a\xac\x40\x85\x83\x80\xaa\x12\x25\xb8\xd1\x6c\xc6\x0a\x08\x00\x84\x61\xc3\x08\x84\x04\xa0\x68\x57\x81\x04\x34\x1e\x1a\x38\x62\x22\xc1\x01\x4a\x2c\x21\xf0\xc3\x44\x85\x11\x6c\x20\x97\x61\x85\x4a\x06\x21\xd8\xb0\xe8\xc5\x07\x18\x1c\x14\xe0\x00</data></write>
		<read echo="ascii"><delim>} </delim><match><data>1- Upload Image\n2- List Images\n3- Remove Image\n4- Display Image\n5- Leave\n} </data></match></read>
		<write echo="ascii"><data>1\n</data></write>
		<read echo="ascii"><delim>: </delim><match><data>Image Name: </data></match></read>
		<write echo="ascii"><data>vzdkcu\n</data></write>
		<write echo="ascii"><data>\x16\x00\xde\xb6\xd9\x55\x52\x36\xa6\x92\x0a\x15\xe0\xb1\x86\x81\x0a\xa2\x08\x08\x80\x60\x47\x00</data></write>
		<read echo="ascii"><delim>} </delim><match><data>1- Upload Image\n2- List Images\n3- Remove Image\n4- Display Image\n5- Leave\n} </data></match></read>
		<write echo="ascii"><data>1\n</data></write>
		<read echo="ascii"><delim>: </delim><match><data>Image Name: </data></match></read>
		<write echo="ascii"><data>mmjrh\n</data></write>
		<write echo="ascii"><data>\x62\x03\xcb\x59\x0f\x31\x66\x7a\x00\x00\x7d\x32\xeb\x68\xe8\xc5\x5f\xa9\x60\x1a\x25\x02\xc7\x9a\x0e\x41\x94\xb4\x23\xcc\x9f\x2c\xd8\xc5\xf1\x83\x0e\xab\x78\xa9\x94\x86\x47\x28\xbc\x52\x09\xb9\x94\x57\x96\xa9\x36\x34\x84\x0b\x09\xaa\xdd\x9c\xa2\x0d\x24\x23\xe4\xc1\xbe\x9d\x09\x94\x66\x85\x34\x44\x31\x80\x52\xcc\x2f\x88\x17\x7c\x65\xc4\x47\x91\x4e\x86\xbc\x9d\xc0\xee\xed\xa7\x3c\x42\x2b\x21\xd7\x27\x1e\x32\x16\x65\xb9\x11\x8a\xcd\x4a\xd4\x51\xe6\xb4\x4f\x0e\x8c\xb9\x6a\x91\xeb\xab\xa6\x6c\x88\x3d\x91\x97\xd8\xcf\xa5\x54\xa3\x28\x31\x2e\x9c\x9f\x7a\x88\x87\x8a\xa4\xb7\xba\x59\x92\x53\x34\x42\x89\x93\x4a\x03\xb6\x23\x4e\x5e\x2c\x68\x65\xc9\xd4\xa9\xc6\xb9\x61\xda\xeb\x23\x52\x5a\x56\x40\x64\xda\xf0\x48\xda\x72\xd0\x43\xe9\x84\xab\x4e\xa5\x3e\xc1\xb0\x45\x12\x45\x45\x69\xb5\xd8\xf4\xe1\x9f\x36\x56\x05\x18\xa8\x4c\x44\x9a\xd1\x95\x81\xd7\x11\x9d\x68\xe9\x01\xa0\xa7\xaa\x90\x3d\x2a\x6a\x24\xe0\x98\x46\x18\x1a\x99\x31\x14\xd9\x08\x85\x78\xd1\xf0\xe4\x95\x5e\x18\xd6\x5b\x51\x27\x60\x03\x5c\xc8\x7c\x5b\x94\x2a\x0f\x50\x5a\xfc\x69\x2f\x57\x40\x10\x0d\x75\xf8\x02\x09\xc7\xa3\x5e\x18\x26\xa5\x6b\x14\x2e\x2e\xc8\x51\x32\xd0\x54\x69\x09\x61\xb8\x74\xe1\x8c\x33\x19\xcd\x76\x61\xd4\x8e\x56\x88\x41\xc1\x27\xeb\x97\x67\x66\x41\x37\x0f\x04\x46\x17\x71\x3d\x99\xd1\x4a\x42\x06\x46\xa1\x13\xa5\x0f\x5c\x38\x1e\x4a\x92\x34\x64\x0f\x54\x19\x61\xb4\x6a\x18\xd4\xa7\x3c\xd0\xf2\x21\xde\x96\x0a\xa8\x63\x39\x14\x49\x1a\x10\xc4\x5a\xb9\x53\xde\x42\x6e\x6c\xdd\xeb\xe5\x22\x06\x96\xf9\x23\x58\x85\xc2\xb7\x15\x39\x89\xc7\x08\xde\x87\x44\xfd\x8b\x41\x4b\xc2\x8e\x35\x72\x43\xd5\x96\x10\x58\x5a\x65\xcb\x07\x05\x60\x33\x14\x4c\x25\x48\x6d\x48\xbe\x54\x79\xa0\x74\x12\x6d\xc7\x86\x51\x39\xa4\x26\x16\x35\x33\x66\x5b\x89\xe5\x28\xb2\x42\x71\x23\xf8\x8c\x01\x41\x37\x12\xe4\x47\xad\x60\x42\x75\x54\x75\x02\x4f\x0b\x43\xb2\x3c\x40\x9a\xa6\xa1\xba\xaa\xe8\x12\x57\x01\x69\x96\x89\x69\x48\xd4\xf7\x8a\x5a\x5f\x76\x8d\x35\xab\x8a\x0c\x86\xea\x92\x06\x30\x5b\xc5\x45\x69\xf0\xc0\xb4\xef\xaa\xa1\x1d\x85\x44\x04\x64\xaf\x3e\x69\x35\x88\xcc\x0d\x15\x1c\x32\x11\xc2\x30\x1d\xaa\x90\x28\x7d\x36\x95\xe6\x15\x50\xa0\xf9\xdb\x4b\x58\x56\x74\x4d\xa9\x65\x54\x84\xbe\x17\x6d\x2d\xe5\x64\x03\x1e\x66\x6a\x2a\xd2\x82\x2e\x87\xab\x0c\x9a\xab\x2f\xa2\xac\x14\x2c\x98\xc5\x8e\x47\x8d\x0c\x0e\x2b\x5a\xa6\xe7\x2a\x24\x9a\xb5\x68\xf7\xa6\x1f\x7d\x59\xf8\x36\x37\xcd\x8f\x44\x76\x64\x05\xd1\x5d\x98\x3c\x10\xc0\x31\x65\x4e\xab\xa2\x04\x4c\x47\x50\x91\xcc\x99\x01\x35\x37\x43\x62\xcd\x3e\x7e\xdd\x94\x89\x8c\x12\x74\x70\xf5\xc2\xc1\xa2\x5b\x63\x12\x8b\x07\xa3\xec\xd9\x5e\xbd\x48\x47\xb7\x9c\xdd\x5a\x8c\x84\x75\x29\x8e\x17\x02\x82\xda\x63\x25\xd6\xae\x72\x49\x7b\x81\xaf\xc6\x35\xad\x1e\x2b\x03\xc5\xa9\x10\x8e\xc5\x20\xca\x20\x8f\x31\x57\x39\xd2\x73\x85\xaf\x48\x78\x28\x9b\xdb\x97\x20\x21\x55\x5c\xc1\x99\xcf\x07\xde\x08\x72\x88\x17\x17\x64\x50\xa4\xa4\x30\xb6\x09\xdf\x3b\xbb\x3c\x6b\xda\xe3\x54\x53\x84\x35\xa1\x83\xb3\x11\x14\x64\xf5\x0d\xdb\xc6\xd0\xdc\x81\x55\xaa\x61\x24\x23\xb3\x38\x98\x49\x15\x70\x2f\xbd\x03\x31\xa3\x78\xc6\xc9\xa8\x9c\x35\x75\xaa\xb0\xc0\x8d\xa8\x41\xb2\x02\x24\x4b\x8f\xbb\x49\x61\xe5\x0d\x20\x25\x7e\xe9\x00\x97\xb0\xdb\xdb\x1d\x3e\x1a\x36\x92\xef\x19\x5e\x44\x79\x54\x4e\xea\xc6\x38\x44\x34\x48\x46\x4d\x5a\x5f\x7d\x80\xf4\x6a\x41\xc6\xbe\x9e\x68\x81\x2f\x43\x4c\x4c\xc6\xa3\xd8\x04\xc8\xb2\x18\x59\xa1\xa9\xf7\x1d\xca\xbf\x39\x7a\xf1\xf3\x6c\x32\x90\x3c\x4b\x71\xb3\x43\x04\x2f\x50\x13\x7b\x0b\x12\x28\x2e\x7a\xd8\xe8\xab\xc9\xa6\xae\x25\x5a\x56\xf7\x2b\x80\x00\x00\x7c\x8c</data></write>
		<read echo="ascii"><delim>} </delim><match><data>1- Upload Image\n2- List Images\n3- Remove Image\n4- Display Image\n5- Leave\n} </data></match></read>
		<write echo="ascii"><data>3\n</data></write>
		<read echo="ascii"><delim>: </delim><match><data>Image Name: </data></match></read>
		<write echo="ascii"><data>uxpzi\n</data></write>
		<read echo="ascii"><delim>} </delim><match><data>1- Upload Image\n2- List Images\n3- Remove Image\n4- Display Image\n5- Leave\n} </data></match></read>
		<write echo="ascii"><data>1\n</data></write>
		<read echo="ascii"><delim>: </delim><match><data>Image Name: </data></match></read>
		<write echo="ascii"><data>brijgj\n</data></write>
		<write echo="ascii"><data>\x62\x00\xcb\x59\x0f\x31\x38\x7a\x00\x00\x1c\x38\x35\xb3\x62\x05\x2f\x89\x48\xb5\x20\xd4\xa0\x42\x48\x78\xa4\x78\xa6\x1e\x36\x3d\x62\xf3\x23\xf3\x48\xaa\x44\x95\x2d\xc8\xb5\xe0\x82\x10\x3c\xdb\x6a\xb1\x5a\xae\x58\x81\x0a\xe0\x65\x02\xdb\x16\xf8\xd2\x03\x15\x98\x35\x02\x56\x2d\x76\xed\x56\x12\x94\x9a\x45\x17\xb0\x1a\x83\x06\xf1\x23\x23\xe5\x9e\x94\x3e\xe0\x4d\x20\x6e\x5e\x42\x12\x50\x00\x00\x9b\x94</data></write>
		<read echo="ascii"><delim>} </delim><match><data>1- Upload Image\n2- List Images\n3- Remove Image\n4- Display Image\n5- Leave\n} </data></match></read>
		<write echo="ascii"><data>3\n</data></write>
		<read echo="ascii"><delim>: </delim><match><data>Image Name: </data></match></read>
		<write echo="ascii"><data>mmjrh\n</data></write>
		<read echo="ascii"><delim>} </delim><match><data>1- Upload Image\n2- List Images\n3- Remove Image\n4- Display Image\n5- Leave\n} </data></match></read>
		<write echo="ascii"><data>1\n</data></write>
		<read echo="ascii"><delim>: </delim><match><data>Image Name: </data></match></read>
		<write echo="ascii"><data>miaairz\n</data></write>
		<write echo="ascii"><data>\x1f\x00\xd3\x09\x51\xc3\x9d\xfc\x46\x60\x0d\x58\xd4\x38\x45\xaf\xcb\x24\x4e\x65\x31\x24\xe8\xca\x28\x1e\x25\x89\xc3\x8d\x46\x06\x28</data></write>
		<read echo="ascii"><delim>} </delim><match><data>1- Upload Image\n2- List Images\n3- Remove Image\n4- Display Image\n5- Leave\n} </data></match></read>
		<write echo = "ascii"><data>4\n</data></write>
		<read echo="ascii"><delim>: </delim><match><data>Image Name: </data></match></read>
		<write echo="ascii"><data>llnwvyhbgxyi\n</data></write>
		<read echo= "ascii"><delim>\x20\x20\x20\x20\x65\x20\x20\x43\x20\x20\x20\x20\x20\x20\x20\x0a\x20\x20\x20\x20\x20\x20\x20\x20\x20\x20\x20\x20\x20\x20\x20\x0a\x20\x20\x20\x20\x64\x20\x20\x20\x20\x20\x20\x20\x20\x20\x28\x0a\x20\x22\x20\x20\x45\x20\x20\x20\x20\x20\x20\x20\x20\x20\x20\x0a\x20\x20\x20\x36\x20\x7d\x20\x20\x20\x3a\x20\x20\x20\x20\x20\x0a\x20\x20\x66\x20\x20\x20\x20\x20\x20\x20\x20\x20\x20\x20\x20\x0a\x20\x20\x20\x75\x20\x20\x20\x20\x20\x20\x20\x20\x20\x20\x20\x0a\x20\x20\x20\x20\x20\x34\x20\x20\x20\x20\x20\x20\x20\x20\x20\x0a\x20\x20\x20\x20\x20\x20\x72\x20\x20\x20\x20\x20\x20\x20\x75\x0a\x20\x20\x20\x20\x20\x20\x20\x20\x20\x20\x47\x20\x20\x20\x20\x0a\x20\x20\x2f\x20\x20\x20\x20\x20\x20\x20\x20\x20\x20\x7e\x20\x0a\x20\x20\x71\x20\x20\x20\x20\x20\x20\x20\x20\x20\x20\x20\x43\x0a\x20\x20\x20\x20\x20\x4d\x20\x20\x3d\x20\x20\x7b\x20\x20\x20\x0a\x20\x79\x20\x20\x20\x20\x20\x20\x20\x20\x20\x20\x20\x20\x20\x0a\x20\x20\x20\x20\x20\x20\x20\x20\x20\x20\x20\x20\x20\x20\x20\x0a\x20\x20\x20\x20\x20\x20\x20\x20\x20\x20\x20\x20\x20\x20\x20\n</delim><match><data>\x20\x20\x20\x20\x65\x20\x20\x43\x20\x20\x20\x20\x20\x20\x20\x0a\x20\x20\x20\x20\x20\x20\x20\x20\x20\x20\x20\x20\x20\x20\x20\x0a\x20\x20\x20\x20\x64\x20\x20\x20\x20\x20\x20\x20\x20\x20\x28\x0a\x20\x22\x20\x20\x45\x20\x20\x20\x20\x20\x20\x20\x20\x20\x20\x0a\x20\x20\x20\x36\x20\x7d\x20\x20\x20\x3a\x20\x20\x20\x20\x20\x0a\x20\x20\x66\x20\x20\x20\x20\x20\x20\x20\x20\x20\x20\x20\x20\x0a\x20\x20\x20\x75\x20\x20\x20\x20\x20\x20\x20\x20\x20\x20\x20\x0a\x20\x20\x20\x20\x20\x34\x20\x20\x20\x20\x20\x20\x20\x20\x20\x0a\x20\x20\x20\x20\x20\x20\x72\x20\x20\x20\x20\x20\x20\x20\x75\x0a\x20\x20\x20\x20\x20\x20\x20\x20\x20\x20\x47\x20\x20\x20\x20\x0a\x20\x20\x2f\x20\x20\x20\x20\x20\x20\x20\x20\x20\x20\x7e\x20\x0a\x20\x20\x71\x20\x20\x20\x20\x20\x20\x20\x20\x20\x20\x20\x43\x0a\x20\x20\x20\x20\x20\x4d\x20\x20\x3d\x20\x20\x7b\x20\x20\x20\x0a\x20\x79\x20\x20\x20\x20\x20\x20\x20\x20\x20\x20\x20\x20\x20\x0a\x20\x20\x20\x20\x20\x20\x20\x20\x20\x20\x20\x20\x20\x20\x20\x0a\x20\x20\x20\x20\x20\x20\x20\x20\x20\x20\x20\x20\x20\x20\x20\n</data></match></read>
		<read echo="ascii"><delim>} </delim><match><data>1- Upload Image\n2- List Images\n3- Remove Image\n4- Display Image\n5- Leave\n} </data></match></read>
		<write echo="ascii"><data>1\n</data></write>
		<read echo="ascii"><delim>: </delim><match><data>Image Name: </data></match></read>
		<write echo="ascii"><data>gzihvdzie\n</data></write>
		<write echo="ascii"><data>\x24\x00\xde\xb6\xd9\x55\x44\x7f\x36\x72\x8e\x04\x68\x38\x44\x40\x41\x6e\x00\x13\x29\x10\xd1\x42\x03\x76\x38\x26\xb0\xa1\x33\x0c\x06\x8c\x20\x73\x80\x00</data></write>
		<read echo="ascii"><delim>} </delim><match><data>1- Upload Image\n2- List Images\n3- Remove Image\n4- Display Image\n5- Leave\n} </data></match></read>
		<write echo="ascii"><data>3\n</data></write>
		<read echo="ascii"><delim>: </delim><match><data>Image Name: </data></match></read>
		<write echo="ascii"><data>brijgj\n</data></write>
		<read echo="ascii"><delim>} </delim><match><data>1- Upload Image\n2- List Images\n3- Remove Image\n4- Display Image\n5- Leave\n} </data></match></read>
		<write echo="ascii"><data>1\n</data></write>
		<read echo="ascii"><delim>: </delim><match><data>Image Name: </data></match></read>
		<write echo="ascii"><data>pyhjpzqupyi\n</data></write>
		<write echo="ascii"><data>\x1a\x00\xd3\x09\x51\xc3\x2a\x88\x24\xe0\x02\x52\x15\x48\x91\x02\x42\x05\x12\x08\xa9\x13\xc3\x06\x8d\x08\x2c\x10</data></write>
		<read echo="ascii"><delim>} </delim><match><data>1- Upload Image\n2- List Images\n3- Remove Image\n4- Display Image\n5- Leave\n} </data></match></read>
		<write echo="ascii"><data>2\n</data></write>
		<read echo="ascii"><delim>\n</delim><match><data>pyhjpzqupyi\n</data></match></read>
		<read echo="ascii"><delim>\n</delim><match><data>gzihvdzie\n</data></match></read>
		<read echo="ascii"><delim>\n</delim><match><data>miaairz\n</data></match></read>
		<read echo="ascii"><delim>\n</delim><match><data>vzdkcu\n</data></match></read>
		<read echo="ascii"><delim>\n</delim><match><data>llnwvyhbgxyi\n</data></match></read>
		<read echo="ascii"><delim>\n</delim><match><data>kwlpsvnpykuovu\n</data></match></read>
		<read echo="ascii"><delim>\n</delim><match><data>tkaaozbqc\n</data></match></read>
		<read echo="ascii"><delim>} </delim><match><data>1- Upload Image\n2- List Images\n3- Remove Image\n4- Display Image\n5- Leave\n} </data></match></read>
		<write echo="ascii"><data>1\n</data></write>
		<read echo="ascii"><delim>: </delim><match><data>Image Name: </data></match></read>
		<write echo="ascii"><data>bsehwpkyjeob\n</data></write>
		<write echo="ascii"><data>\x1d\x00\x24\xc7\xee\x85\x91\x91\x00\x00\x8d\x47\x05\x6b\x56\x24\x48\xa7\x60\x04\x59\x93\x67\xc6\xb1\x5a\xc4\x68\x80\x21\x43</data></write>
		<read echo="ascii"><delim>} </delim><match><data>1- Upload Image\n2- List Images\n3- Remove Image\n4- Display Image\n5- Leave\n} </data></match></read>
		<write echo = "ascii"><data>4\n</data></write>
		<read echo="ascii"><delim>: </delim><match><data>Image Name: </data></match></read>
		<write echo="ascii"><data>kwlpsvnpykuovu\n</data></write>
		<read echo= "ascii"><delim>\x4f\x69\x65\x61\x67\x54\x59\x53\x4c\x2e\x27\x3a\x3e\x77\x26\x52\x6c\x0a\x2c\x73\x5e\x4c\x25\x3b\x4a\x22\x41\x57\x30\x4b\x3a\x7a\x2a\x3e\x3d\x0a\x72\x2b\x5b\x73\x63\x4f\x5d\x62\x7c\x3a\x7e\x53\x5b\x7d\x35\x49\x30\x0a\x4c\x76\x65\x32\x5e\x60\x46\x5f\x4b\x37\x43\x55\x63\x62\x3a\x66\x22\x0a\x61\x3a\x47\x3c\x71\x5a\x49\x42\x4e\x7b\x65\x57\x33\x5f\x26\x29\x5c\x0a\x27\x4d\x57\x36\x36\x76\x5b\x57\x6b\x4a\x20\x34\x58\x69\x59\x72\x7e\x0a\x57\x6b\x45\x32\x77\x69\x75\x5b\x3b\x43\x4c\x20\x4c\x75\x6f\x5f\x55\x0a\x4d\x2a\x71\x21\x6d\x61\x49\x5d\x7d\x3a\x3f\x21\x41\x5c\x51\x23\x4d\x0a\x67\x47\x3f\x68\x70\x3e\x5c\x5a\x20\x3b\x65\x5b\x4a\x5d\x47\x2d\x51\x0a\x6c\x46\x6b\x26\x4e\x56\x52\x26\x40\x5c\x25\x69\x61\x41\x4f\x68\x2e\x0a\x45\x5c\x4a\x2e\x45\x56\x7d\x64\x38\x60\x75\x5d\x31\x43\x3f\x63\x7e\x0a\x6f\x5b\x4c\x5a\x59\x2f\x40\x5e\x74\x57\x58\x5b\x60\x3f\x6d\x63\x4d\x0a\x34\x47\x38\x7e\x32\x7c\x6f\x57\x53\x65\x35\x4a\x4b\x68\x37\x50\x34\x0a\x74\x4c\x50\x3d\x70\x7c\x71\x2e\x3c\x47\x4c\x5b\x46\x67\x60\x30\x54\x0a\x55\x4b\x62\x5d\x49\x7a\x31\x69\x59\x40\x6e\x66\x26\x35\x7e\x38\x7b\x0a\x2d\x29\x38\x73\x2f\x6c\x53\x69\x4f\x2d\x63\x2a\x5f\x47\x47\x6b\x27\x0a\x69\x47\x45\x5d\x57\x30\x57\x5a\x41\x7d\x4f\x47\x68\x2a\x36\x7b\x64\x0a\x38\x53\x65\x5b\x70\x7e\x54\x30\x34\x31\x4e\x2c\x5d\x63\x61\x65\x2a\x0a\x65\x3c\x25\x4e\x71\x3b\x76\x5c\x54\x58\x37\x28\x3c\x5b\x6a\x39\x72\x0a\x3a\x33\x4b\x25\x44\x30\x4b\x24\x43\x66\x78\x42\x77\x7c\x34\x37\x3d\x0a\x29\x35\x50\x5d\x2d\x76\x43\x56\x72\x7e\x2e\x3a\x3e\x66\x73\x3f\x61\x0a\x38\x72\x67\x3e\x20\x4a\x5c\x31\x2c\x38\x70\x32\x40\x6b\x55\x50\x27\x0a\x4d\x27\x6f\x3b\x22\x2d\x3a\x67\x4c\x61\x55\x30\x6a\x50\x27\x60\x76\x0a\x2c\x24\x75\x6e\x4c\x42\x5e\x77\x62\x67\x4f\x4e\x43\x48\x36\x66\x38\x0a\x28\x35\x6d\x71\x4b\x35\x7b\x43\x78\x49\x51\x52\x31\x4d\x3a\x24\x43\x0a\x44\x59\x29\x29\x24\x31\x69\x77\x7e\x59\x35\x40\x4f\x3c\x66\x5d\x6e\x0a\x47\x36\x32\x3a\x22\x22\x31\x6f\x6d\x6a\x4e\x6e\x37\x4f\x3e\x74\x73\x0a\x65\x44\x4e\x33\x71\x4e\x6c\x2b\x67\x49\x75\x67\x2f\x30\x54\x78\x78\x0a\x4e\x51\x6c\x70\x34\x4d\x24\x2d\x2a\x38\x6e\x2c\x7b\x38\x64\x43\x61\x0a\x63\x2a\x45\x48\x4a\x70\x2c\x4c\x4d\x7a\x5b\x70\x2e\x4f\x6e\x74\x78\x0a\x27\x79\x48\x29\x5b\x5f\x6e\x7a\x78\x46\x28\x46\x2f\x24\x61\x22\x40\n</delim><match><data>\x4f\x69\x65\x61\x67\x54\x59\x53\x4c\x2e\x27\x3a\x3e\x77\x26\x52\x6c\x0a\x2c\x73\x5e\x4c\x25\x3b\x4a\x22\x41\x57\x30\x4b\x3a\x7a\x2a\x3e\x3d\x0a\x72\x2b\x5b\x73\x63\x4f\x5d\x62\x7c\x3a\x7e\x53\x5b\x7d\x35\x49\x30\x0a\x4c\x76\x65\x32\x5e\x60\x46\x5f\x4b\x37\x43\x55\x63\x62\x3a\x66\x22\x0a\x61\x3a\x47\x3c\x71\x5a\x49\x42\x4e\x7b\x65\x57\x33\x5f\x26\x29\x5c\x0a\x27\x4d\x57\x36\x36\x76\x5b\x57\x6b\x4a\x20\x34\x58\x69\x59\x72\x7e\x0a\x57\x6b\x45\x32\x77\x69\x75\x5b\x3b\x43\x4c\x20\x4c\x75\x6f\x5f\x55\x0a\x4d\x2a\x71\x21\x6d\x61\x49\x5d\x7d\x3a\x3f\x21\x41\x5c\x51\x23\x4d\x0a\x67\x47\x3f\x68\x70\x3e\x5c\x5a\x20\x3b\x65\x5b\x4a\x5d\x47\x2d\x51\x0a\x6c\x46\x6b\x26\x4e\x56\x52\x26\x40\x5c\x25\x69\x61\x41\x4f\x68\x2e\x0a\x45\x5c\x4a\x2e\x45\x56\x7d\x64\x38\x60\x75\x5d\x31\x43\x3f\x63\x7e\x0a\x6f\x5b\x4c\x5a\x59\x2f\x40\x5e\x74\x57\x58\x5b\x60\x3f\x6d\x63\x4d\x0a\x34\x47\x38\x7e\x32\x7c\x6f\x57\x53\x65\x35\x4a\x4b\x68\x37\x50\x34\x0a\x74\x4c\x50\x3d\x70\x7c\x71\x2e\x3c\x47\x4c\x5b\x46\x67\x60\x30\x54\x0a\x55\x4b\x62\x5d\x49\x7a\x31\x69\x59\x40\x6e\x66\x26\x35\x7e\x38\x7b\x0a\x2d\x29\x38\x73\x2f\x6c\x53\x69\x4f\x2d\x63\x2a\x5f\x47\x47\x6b\x27\x0a\x69\x47\x45\x5d\x57\x30\x57\x5a\x41\x7d\x4f\x47\x68\x2a\x36\x7b\x64\x0a\x38\x53\x65\x5b\x70\x7e\x54\x30\x34\x31\x4e\x2c\x5d\x63\x61\x65\x2a\x0a\x65\x3c\x25\x4e\x71\x3b\x76\x5c\x54\x58\x37\x28\x3c\x5b\x6a\x39\x72\x0a\x3a\x33\x4b\x25\x44\x30\x4b\x24\x43\x66\x78\x42\x77\x7c\x34\x37\x3d\x0a\x29\x35\x50\x5d\x2d\x76\x43\x56\x72\x7e\x2e\x3a\x3e\x66\x73\x3f\x61\x0a\x38\x72\x67\x3e\x20\x4a\x5c\x31\x2c\x38\x70\x32\x40\x6b\x55\x50\x27\x0a\x4d\x27\x6f\x3b\x22\x2d\x3a\x67\x4c\x61\x55\x30\x6a\x50\x27\x60\x76\x0a\x2c\x24\x75\x6e\x4c\x42\x5e\x77\x62\x67\x4f\x4e\x43\x48\x36\x66\x38\x0a\x28\x35\x6d\x71\x4b\x35\x7b\x43\x78\x49\x51\x52\x31\x4d\x3a\x24\x43\x0a\x44\x59\x29\x29\x24\x31\x69\x77\x7e\x59\x35\x40\x4f\x3c\x66\x5d\x6e\x0a\x47\x36\x32\x3a\x22\x22\x31\x6f\x6d\x6a\x4e\x6e\x37\x4f\x3e\x74\x73\x0a\x65\x44\x4e\x33\x71\x4e\x6c\x2b\x67\x49\x75\x67\x2f\x30\x54\x78\x78\x0a\x4e\x51\x6c\x70\x34\x4d\x24\x2d\x2a\x38\x6e\x2c\x7b\x38\x64\x43\x61\x0a\x63\x2a\x45\x48\x4a\x70\x2c\x4c\x4d\x7a\x5b\x70\x2e\x4f\x6e\x74\x78\x0a\x27\x79\x48\x29\x5b\x5f\x6e\x7a\x78\x46\x28\x46\x2f\x24\x61\x22\x40\n</data></match></read>
		<read echo="ascii"><delim>} </delim><match><data>1- Upload Image\n2- List Images\n3- Remove Image\n4- Display Image\n5- Leave\n} </data></match></read>
		<write echo = "ascii"><data>4\n</data></write>
		<read echo="ascii"><delim>: </delim><match><data>Image Name: </data></match></read>
		<write echo="ascii"><data>tkaaozbqc\n</data></write>
		<read echo= "ascii"><delim>\x20\x20\x20\x20\x20\x20\x20\x20\x20\x20\x20\x20\x20\x20\x2e\x20\x20\x20\x20\x20\x20\x20\x20\x20\x20\x20\x20\x20\x20\x20\x20\x20\x20\x20\x20\x2e\x0a\x20\x20\x20\x20\x20\x20\x20\x20\x20\x20\x20\x20\x20\x20\x2e\x20\x20\x20\x20\x20\x20\x20\x20\x20\x20\x20\x20\x20\x20\x20\x20\x20\x20\x20\x20\x20\x0a\x20\x20\x20\x20\x20\x20\x20\x20\x20\x20\x20\x20\x20\x20\x20\x20\x20\x20\x20\x20\x20\x20\x20\x20\x20\x20\x20\x20\x20\x20\x20\x20\x20\x20\x20\x20\x0a\x20\x20\x20\x20\x20\x20\x20\x20\x20\x20\x20\x20\x20\x20\x20\x20\x20\x20\x20\x20\x20\x20\x20\x20\x20\x20\x20\x20\x20\x20\x20\x20\x20\x20\x20\x20\x0a\x20\x20\x20\x20\x20\x20\x20\x20\x20\x20\x20\x20\x20\x20\x20\x20\x20\x20\x20\x20\x20\x20\x20\x20\x20\x20\x20\x20\x20\x20\x20\x20\x20\x20\x20\x20\x0a\x20\x20\x20\x20\x20\x20\x20\x20\x20\x20\x20\x20\x20\x20\x2e\x20\x20\x20\x20\x20\x20\x20\x20\x20\x20\x20\x20\x20\x20\x20\x20\x20\x20\x20\x20\x20\x0a\x20\x20\x20\x20\x20\x20\x2e\x20\x20\x20\x20\x20\x20\x20\x20\x20\x20\x20\x20\x20\x20\x2e\x20\x20\x20\x20\x2e\x20\x20\x20\x20\x20\x20\x20\x20\x20\x0a\x20\x20\x20\x20\x20\x20\x20\x20\x20\x20\x20\x20\x2e\x20\x20\x20\x20\x20\x20\x20\x20\x20\x20\x20\x20\x20\x20\x20\x20\x20\x20\x20\x20\x20\x20\x20\x0a\x20\x20\x20\x20\x20\x20\x20\x20\x20\x20\x20\x20\x20\x20\x20\x20\x2e\x20\x20\x20\x20\x20\x20\x20\x20\x20\x20\x20\x20\x20\x20\x20\x20\x20\x20\x20\x0a\x20\x20\x20\x20\x20\x20\x20\x20\x20\x20\x20\x20\x20\x20\x20\x20\x20\x20\x20\x2e\x20\x20\x20\x20\x20\x20\x20\x20\x20\x20\x20\x20\x20\x20\x20\x2e\x0a\x20\x20\x20\x20\x20\x20\x20\x20\x20\x20\x20\x20\x20\x20\x20\x20\x20\x20\x20\x20\x20\x20\x20\x20\x20\x20\x20\x20\x20\x20\x20\x20\x20\x20\x20\x20\x0a\x20\x20\x20\x20\x20\x20\x20\x20\x20\x20\x20\x20\x20\x20\x20\x20\x20\x20\x20\x20\x20\x20\x20\x20\x20\x20\x20\x20\x20\x20\x20\x20\x20\x20\x20\x20\x0a\x20\x20\x20\x20\x20\x20\x20\x20\x20\x20\x20\x20\x20\x20\x20\x20\x20\x20\x20\x20\x20\x20\x20\x20\x20\x20\x20\x20\x20\x20\x20\x20\x20\x20\x20\x20\x0a\x20\x20\x20\x20\x20\x20\x20\x20\x20\x20\x20\x20\x20\x20\x20\x20\x20\x20\x20\x20\x20\x20\x20\x20\x20\x20\x20\x20\x20\x20\x20\x20\x20\x20\x20\x20\x0a\x20\x20\x20\x20\x20\x20\x20\x20\x20\x20\x20\x20\x20\x20\x20\x20\x20\x20\x20\x20\x20\x20\x20\x20\x20\x20\x20\x20\x20\x20\x20\x20\x20\x20\x20\x20\x0a\x20\x20\x20\x20\x20\x20\x20\x20\x20\x20\x20\x20\x20\x20\x20\x20\x20\x20\x20\x20\x20\x20\x20\x20\x20\x20\x20\x20\x20\x20\x20\x20\x20\x20\x20\x20\x0a\x20\x20\x20\x20\x20\x20\x20\x20\x20\x20\x20\x20\x20\x20\x20\x20\x20\x20\x20\x20\x20\x20\x20\x20\x20\x20\x20\x20\x20\x20\x20\x20\x20\x20\x20\x20\x0a\x20\x20\x20\x20\x20\x20\x20\x20\x20\x20\x20\x20\x20\x20\x20\x20\x20\x20\x20\x20\x20\x20\x20\x20\x20\x20\x20\x20\x20\x2e\x20\x20\x20\x2e\x20\x20\x0a\x20\x20\x20\x20\x20\x20\x20\x20\x20\x20\x20\x20\x20\x20\x20\x20\x20\x20\x20\x20\x20\x20\x20\x20\x20\x2e\x20\x20\x20\x20\x20\x20\x20\x20\x20\x20\x0a\x20\x20\x20\x20\x20\x2e\x20\x20\x20\x20\x20\x20\x20\x20\x20\x20\x20\x20\x20\x20\x20\x20\x20\x20\x20\x20\x20\x20\x20\x20\x20\x20\x20\x20\x20\x20\n</delim><match><data>\x20\x20\x20\x20\x20\x20\x20\x20\x20\x20\x20\x20\x20\x20\x2e\x20\x20\x20\x20\x20\x20\x20\x20\x20\x20\x20\x20\x20\x20\x20\x20\x20\x20\x20\x20\x2e\x0a\x20\x20\x20\x20\x20\x20\x20\x20\x20\x20\x20\x20\x20\x20\x2e\x20\x20\x20\x20\x20\x20\x20\x20\x20\x20\x20\x20\x20\x20\x20\x20\x20\x20\x20\x20\x20\x0a\x20\x20\x20\x20\x20\x20\x20\x20\x20\x20\x20\x20\x20\x20\x20\x20\x20\x20\x20\x20\x20\x20\x20\x20\x20\x20\x20\x20\x20\x20\x20\x20\x20\x20\x20\x20\x0a\x20\x20\x20\x20\x20\x20\x20\x20\x20\x20\x20\x20\x20\x20\x20\x20\x20\x20\x20\x20\x20\x20\x20\x20\x20\x20\x20\x20\x20\x20\x20\x20\x20\x20\x20\x20\x0a\x20\x20\x20\x20\x20\x20\x20\x20\x20\x20\x20\x20\x20\x20\x20\x20\x20\x20\x20\x20\x20\x20\x20\x20\x20\x20\x20\x20\x20\x20\x20\x20\x20\x20\x20\x20\x0a\x20\x20\x20\x20\x20\x20\x20\x20\x20\x20\x20\x20\x20\x20\x2e\x20\x20\x20\x20\x20\x20\x20\x20\x20\x20\x20\x20\x20\x20\x20\x20\x20\x20\x20\x20\x20\x0a\x20\x20\x20\x20\x20\x20\x2e\x20\x20\x20\x20\x20\x20\x20\x20\x20\x20\x20\x20\x20\x20\x2e\x20\x20\x20\x20\x2e\x20\x20\x20\x20\x20\x20\x20\x20\x20\x0a\x20\x20\x20\x20\x20\x20\x20\x20\x20\x20\x20\x20\x2e\x20\x20\x20\x20\x20\x20\x20\x20\x20\x20\x20\x20\x20\x20\x20\x20\x20\x20\x20\x20\x20\x20\x20\x0a\x20\x20\x20\x20\x20\x20\x20\x20\x20\x20\x20\x20\x20\x20\x20\x20\x2e\x20\x20\x20\x20\x20\x20\x20\x20\x20\x20\x20\x20\x20\x20\x20\x20\x20\x20\x20\x0a\x20\x20\x20\x20\x20\x20\x20\x20\x20\x20\x20\x20\x20\x20\x20\x20\x20\x20\x20\x2e\x20\x20\x20\x20\x20\x20\x20\x20\x20\x20\x20\x20\x20\x20\x20\x2e\x0a\x20\x20\x20\x20\x20\x20\x20\x20\x20\x20\x20\x20\x20\x20\x20\x20\x20\x20\x20\x20\x20\x20\x20\x20\x20\x20\x20\x20\x20\x20\x20\x20\x20\x20\x20\x20\x0a\x20\x20\x20\x20\x20\x20\x20\x20\x20\x20\x20\x20\x20\x20\x20\x20\x20\x20\x20\x20\x20\x20\x20\x20\x20\x20\x20\x20\x20\x20\x20\x20\x20\x20\x20\x20\x0a\x20\x20\x20\x20\x20\x20\x20\x20\x20\x20\x20\x20\x20\x20\x20\x20\x20\x20\x20\x20\x20\x20\x20\x20\x20\x20\x20\x20\x20\x20\x20\x20\x20\x20\x20\x20\x0a\x20\x20\x20\x20\x20\x20\x20\x20\x20\x20\x20\x20\x20\x20\x20\x20\x20\x20\x20\x20\x20\x20\x20\x20\x20\x20\x20\x20\x20\x20\x20\x20\x20\x20\x20\x20\x0a\x20\x20\x20\x20\x20\x20\x20\x20\x20\x20\x20\x20\x20\x20\x20\x20\x20\x20\x20\x20\x20\x20\x20\x20\x20\x20\x20\x20\x20\x20\x20\x20\x20\x20\x20\x20\x0a\x20\x20\x20\x20\x20\x20\x20\x20\x20\x20\x20\x20\x20\x20\x20\x20\x20\x20\x20\x20\x20\x20\x20\x20\x20\x20\x20\x20\x20\x20\x20\x20\x20\x20\x20\x20\x0a\x20\x20\x20\x20\x20\x20\x20\x20\x20\x20\x20\x20\x20\x20\x20\x20\x20\x20\x20\x20\x20\x20\x20\x20\x20\x20\x20\x20\x20\x20\x20\x20\x20\x20\x20\x20\x0a\x20\x20\x20\x20\x20\x20\x20\x20\x20\x20\x20\x20\x20\x20\x20\x20\x20\x20\x20\x20\x20\x20\x20\x20\x20\x20\x20\x20\x20\x2e\x20\x20\x20\x2e\x20\x20\x0a\x20\x20\x20\x20\x20\x20\x20\x20\x20\x20\x20\x20\x20\x20\x20\x20\x20\x20\x20\x20\x20\x20\x20\x20\x20\x2e\x20\x20\x20\x20\x20\x20\x20\x20\x20\x20\x0a\x20\x20\x20\x20\x20\x2e\x20\x20\x20\x20\x20\x20\x20\x20\x20\x20\x20\x20\x20\x20\x20\x20\x20\x20\x20\x20\x20\x20\x20\x20\x20\x20\x20\x20\x20\x20\n</data></match></read>
		<read echo="ascii"><delim>} </delim><match><data>1- Upload Image\n2- List Images\n3- Remove Image\n4- Display Image\n5- Leave\n} </data></match></read>
		<write echo = "ascii"><data>4\n</data></write>
		<read echo="ascii"><delim>: </delim><match><data>Image Name: </data></match></read>
		<write echo="ascii"><data>bsehwpkyjeob\n</data></write>
		<read echo= "ascii"><delim>\x20\x20\x20\x20\x20\x20\x20\x20\x20\x20\x20\x20\x20\x20\x20\x20\x20\x20\x20\x20\x20\x20\x20\x20\x20\x20\x20\x20\x20\x20\x20\x2e\x20\x20\x20\x20\x0a\x20\x20\x20\x20\x20\x20\x20\x20\x20\x20\x20\x20\x20\x20\x20\x20\x20\x20\x20\x20\x20\x20\x20\x20\x20\x20\x20\x20\x20\x20\x20\x20\x20\x20\x20\x20\x0a\x20\x20\x20\x20\x20\x20\x20\x20\x20\x20\x20\x20\x20\x20\x20\x20\x20\x20\x20\x20\x20\x20\x20\x20\x20\x20\x20\x20\x20\x20\x20\x20\x20\x20\x20\x20\x0a\x20\x20\x20\x20\x20\x20\x20\x20\x20\x20\x20\x20\x20\x20\x20\x20\x20\x20\x20\x20\x20\x20\x20\x20\x20\x20\x20\x20\x20\x20\x20\x20\x20\x2e\x20\x20\x0a\x20\x20\x20\x20\x20\x20\x20\x20\x20\x20\x20\x20\x20\x20\x20\x20\x20\x20\x20\x20\x20\x20\x20\x20\x20\x20\x20\x20\x20\x20\x20\x20\x20\x20\x20\x20\x0a\x20\x20\x20\x20\x20\x20\x20\x20\x20\x20\x20\x20\x20\x20\x20\x20\x20\x20\x20\x20\x20\x20\x20\x20\x20\x20\x20\x20\x20\x20\x20\x20\x20\x20\x20\x2e\x0a\x20\x20\x20\x20\x20\x20\x20\x20\x20\x20\x20\x2e\x20\x20\x20\x20\x20\x20\x20\x20\x2e\x20\x20\x20\x20\x20\x20\x20\x20\x20\x20\x20\x20\x20\x20\x20\x0a\x20\x20\x20\x20\x20\x20\x20\x20\x20\x20\x20\x20\x20\x20\x20\x20\x20\x20\x20\x20\x20\x20\x20\x20\x20\x20\x20\x20\x20\x20\x20\x20\x20\x20\x20\x20\x0a\x20\x20\x20\x20\x20\x20\x20\x20\x20\x20\x20\x20\x20\x20\x20\x20\x20\x20\x20\x20\x20\x20\x20\x20\x20\x20\x20\x2e\x20\x20\x20\x20\x20\x20\x20\x20\x0a\x20\x20\x20\x20\x20\x20\x20\x20\x20\x20\x20\x20\x20\x20\x20\x20\x20\x20\x20\x20\x20\x20\x20\x20\x20\x20\x20\x20\x20\x20\x20\x20\x20\x20\x20\x20\x0a\x20\x20\x20\x20\x20\x20\x20\x20\x20\x20\x20\x20\x20\x20\x20\x20\x20\x20\x20\x20\x20\x20\x20\x20\x20\x20\x20\x20\x20\x20\x20\x20\x20\x20\x20\x20\x0a\x20\x20\x20\x20\x20\x20\x20\x20\x20\x20\x20\x20\x20\x20\x20\x20\x20\x20\x20\x20\x20\x20\x20\x20\x20\x20\x20\x20\x20\x20\x20\x20\x20\x20\x20\x20\x0a\x20\x20\x20\x20\x20\x20\x20\x20\x20\x20\x20\x20\x20\x20\x20\x20\x20\x20\x20\x20\x20\x20\x20\x20\x20\x20\x20\x20\x20\x20\x20\x20\x20\x20\x20\x20\x0a\x20\x20\x20\x20\x20\x20\x20\x20\x20\x20\x20\x20\x20\x20\x20\x20\x20\x20\x20\x20\x20\x20\x20\x2e\x20\x20\x20\x20\x20\x20\x20\x20\x20\x20\x20\x20\x0a\x20\x20\x20\x20\x20\x20\x20\x20\x20\x20\x20\x20\x20\x20\x20\x20\x20\x20\x20\x20\x20\x20\x20\x20\x20\x20\x20\x20\x20\x20\x20\x20\x20\x20\x20\x20\x0a\x20\x20\x20\x20\x20\x20\x20\x20\x20\x20\x20\x20\x20\x20\x20\x20\x20\x20\x20\x20\x20\x20\x20\x20\x20\x20\x20\x20\x20\x20\x20\x20\x20\x20\x20\x20\x0a\x20\x20\x20\x20\x20\x20\x20\x20\x20\x20\x20\x20\x20\x20\x20\x20\x20\x20\x20\x20\x20\x20\x20\x20\x20\x20\x20\x20\x20\x20\x20\x20\x20\x20\x20\x20\x0a\x20\x20\x20\x20\x20\x20\x20\x20\x20\x20\x20\x20\x20\x20\x20\x20\x20\x20\x20\x20\x20\x20\x20\x20\x20\x20\x20\x20\x20\x2e\x20\x20\x20\x20\x20\x20\x0a\x20\x20\x20\x20\x20\x20\x20\x20\x20\x20\x20\x20\x20\x20\x20\x20\x20\x20\x20\x20\x20\x20\x20\x20\x20\x20\x20\x20\x20\x20\x20\x20\x20\x20\x20\x20\x0a\x20\x20\x20\x20\x20\x20\x20\x20\x20\x20\x20\x20\x20\x20\x20\x20\x20\x20\x20\x20\x20\x20\x20\x20\x20\x20\x20\x20\x20\x20\x20\x20\x20\x20\x20\x20\x0a\x20\x20\x20\x20\x20\x20\x20\x20\x20\x20\x20\x20\x20\x20\x20\x20\x20\x20\x20\x20\x20\x20\x20\x20\x20\x20\x20\x20\x20\x20\x20\x20\x20\x20\x20\x20\x0a\x20\x20\x20\x20\x20\x20\x20\x20\x20\x20\x20\x20\x20\x20\x20\x20\x20\x20\x20\x20\x20\x20\x20\x20\x20\x20\x20\x20\x20\x20\x20\x20\x20\x20\x20\x20\x0a\x20\x20\x20\x2e\x20\x20\x20\x20\x20\x20\x20\x2e\x20\x20\x20\x20\x20\x20\x20\x20\x20\x20\x20\x20\x20\x20\x20\x20\x20\x20\x20\x20\x20\x20\x20\x20\x0a\x20\x20\x20\x20\x20\x20\x20\x20\x20\x20\x20\x20\x20\x20\x20\x20\x20\x20\x20\x20\x20\x20\x20\x20\x20\x20\x20\x20\x20\x20\x20\x20\x20\x20\x20\x20\x0a\x20\x20\x20\x20\x20\x20\x20\x20\x20\x2e\x20\x20\x20\x20\x20\x20\x2e\x20\x20\x20\x20\x20\x20\x20\x20\x20\x20\x20\x20\x20\x20\x20\x20\x20\x20\x20\n</delim><match><data>\x20\x20\x20\x20\x20\x20\x20\x20\x20\x20\x20\x20\x20\x20\x20\x20\x20\x20\x20\x20\x20\x20\x20\x20\x20\x20\x20\x20\x20\x20\x20\x2e\x20\x20\x20\x20\x0a\x20\x20\x20\x20\x20\x20\x20\x20\x20\x20\x20\x20\x20\x20\x20\x20\x20\x20\x20\x20\x20\x20\x20\x20\x20\x20\x20\x20\x20\x20\x20\x20\x20\x20\x20\x20\x0a\x20\x20\x20\x20\x20\x20\x20\x20\x20\x20\x20\x20\x20\x20\x20\x20\x20\x20\x20\x20\x20\x20\x20\x20\x20\x20\x20\x20\x20\x20\x20\x20\x20\x20\x20\x20\x0a\x20\x20\x20\x20\x20\x20\x20\x20\x20\x20\x20\x20\x20\x20\x20\x20\x20\x20\x20\x20\x20\x20\x20\x20\x20\x20\x20\x20\x20\x20\x20\x20\x20\x2e\x20\x20\x0a\x20\x20\x20\x20\x20\x20\x20\x20\x20\x20\x20\x20\x20\x20\x20\x20\x20\x20\x20\x20\x20\x20\x20\x20\x20\x20\x20\x20\x20\x20\x20\x20\x20\x20\x20\x20\x0a\x20\x20\x20\x20\x20\x20\x20\x20\x20\x20\x20\x20\x20\x20\x20\x20\x20\x20\x20\x20\x20\x20\x20\x20\x20\x20\x20\x20\x20\x20\x20\x20\x20\x20\x20\x2e\x0a\x20\x20\x20\x20\x20\x20\x20\x20\x20\x20\x20\x2e\x20\x20\x20\x20\x20\x20\x20\x20\x2e\x20\x20\x20\x20\x20\x20\x20\x20\x20\x20\x20\x20\x20\x20\x20\x0a\x20\x20\x20\x20\x20\x20\x20\x20\x20\x20\x20\x20\x20\x20\x20\x20\x20\x20\x20\x20\x20\x20\x20\x20\x20\x20\x20\x20\x20\x20\x20\x20\x20\x20\x20\x20\x0a\x20\x20\x20\x20\x20\x20\x20\x20\x20\x20\x20\x20\x20\x20\x20\x20\x20\x20\x20\x20\x20\x20\x20\x20\x20\x20\x20\x2e\x20\x20\x20\x20\x20\x20\x20\x20\x0a\x20\x20\x20\x20\x20\x20\x20\x20\x20\x20\x20\x20\x20\x20\x20\x20\x20\x20\x20\x20\x20\x20\x20\x20\x20\x20\x20\x20\x20\x20\x20\x20\x20\x20\x20\x20\x0a\x20\x20\x20\x20\x20\x20\x20\x20\x20\x20\x20\x20\x20\x20\x20\x20\x20\x20\x20\x20\x20\x20\x20\x20\x20\x20\x20\x20\x20\x20\x20\x20\x20\x20\x20\x20\x0a\x20\x20\x20\x20\x20\x20\x20\x20\x20\x20\x20\x20\x20\x20\x20\x20\x20\x20\x20\x20\x20\x20\x20\x20\x20\x20\x20\x20\x20\x20\x20\x20\x20\x20\x20\x20\x0a\x20\x20\x20\x20\x20\x20\x20\x20\x20\x20\x20\x20\x20\x20\x20\x20\x20\x20\x20\x20\x20\x20\x20\x20\x20\x20\x20\x20\x20\x20\x20\x20\x20\x20\x20\x20\x0a\x20\x20\x20\x20\x20\x20\x20\x20\x20\x20\x20\x20\x20\x20\x20\x20\x20\x20\x20\x20\x20\x20\x20\x2e\x20\x20\x20\x20\x20\x20\x20\x20\x20\x20\x20\x20\x0a\x20\x20\x20\x20\x20\x20\x20\x20\x20\x20\x20\x20\x20\x20\x20\x20\x20\x20\x20\x20\x20\x20\x20\x20\x20\x20\x20\x20\x20\x20\x20\x20\x20\x20\x20\x20\x0a\x20\x20\x20\x20\x20\x20\x20\x20\x20\x20\x20\x20\x20\x20\x20\x20\x20\x20\x20\x20\x20\x20\x20\x20\x20\x20\x20\x20\x20\x20\x20\x20\x20\x20\x20\x20\x0a\x20\x20\x20\x20\x20\x20\x20\x20\x20\x20\x20\x20\x20\x20\x20\x20\x20\x20\x20\x20\x20\x20\x20\x20\x20\x20\x20\x20\x20\x20\x20\x20\x20\x20\x20\x20\x0a\x20\x20\x20\x20\x20\x20\x20\x20\x20\x20\x20\x20\x20\x20\x20\x20\x20\x20\x20\x20\x20\x20\x20\x20\x20\x20\x20\x20\x20\x2e\x20\x20\x20\x20\x20\x20\x0a\x20\x20\x20\x20\x20\x20\x20\x20\x20\x20\x20\x20\x20\x20\x20\x20\x20\x20\x20\x20\x20\x20\x20\x20\x20\x20\x20\x20\x20\x20\x20\x20\x20\x20\x20\x20\x0a\x20\x20\x20\x20\x20\x20\x20\x20\x20\x20\x20\x20\x20\x20\x20\x20\x20\x20\x20\x20\x20\x20\x20\x20\x20\x20\x20\x20\x20\x20\x20\x20\x20\x20\x20\x20\x0a\x20\x20\x20\x20\x20\x20\x20\x20\x20\x20\x20\x20\x20\x20\x20\x20\x20\x20\x20\x20\x20\x20\x20\x20\x20\x20\x20\x20\x20\x20\x20\x20\x20\x20\x20\x20\x0a\x20\x20\x20\x20\x20\x20\x20\x20\x20\x20\x20\x20\x20\x20\x20\x20\x20\x20\x20\x20\x20\x20\x20\x20\x20\x20\x20\x20\x20\x20\x20\x20\x20\x20\x20\x20\x0a\x20\x20\x20\x2e\x20\x20\x20\x20\x20\x20\x20\x2e\x20\x20\x20\x20\x20\x20\x20\x20\x20\x20\x20\x20\x20\x20\x20\x20\x20\x20\x20\x20\x20\x20\x20\x20\x0a\x20\x20\x20\x20\x20\x20\x20\x20\x20\x20\x20\x20\x20\x20\x20\x20\x20\x20\x20\x20\x20\x20\x20\x20\x20\x20\x20\x20\x20\x20\x20\x20\x20\x20\x20\x20\x0a\x20\x20\x20\x20\x20\x20\x20\x20\x20\x2e\x20\x20\x20\x20\x20\x20\x2e\x20\x20\x20\x20\x20\x20\x20\x20\x20\x20\x20\x20\x20\x20\x20\x20\x20\x20\x20\n</data></match></read>
		<read echo="ascii"><delim>} </delim><match><data>1- Upload Image\n2- List Images\n3- Remove Image\n4- Display Image\n5- Leave\n} </data></match></read>
		<write echo = "ascii"><data>4\n</data></write>
		<read echo="ascii"><delim>: </delim><match><data>Image Name: </data></match></read>
		<write echo="ascii"><data>vzdkcu\n</data></write>
		<read echo= "ascii"><delim>\x20\x20\x20\x20\x20\x20\x20\x20\x20\x20\x20\x20\x20\x20\x20\x20\x20\x20\x20\x20\x0a\x20\x20\x20\x20\x20\x20\x20\x20\x20\x20\x20\x20\x20\x20\x20\x20\x20\x20\x20\x20\x0a\x20\x20\x20\x20\x20\x20\x20\x20\x20\x20\x20\x20\x20\x20\x20\x20\x20\x20\x20\x20\x0a\x20\x20\x20\x20\x20\x20\x20\x20\x20\x20\x20\x20\x20\x20\x20\x20\x20\x20\x20\x20\x0a\x20\x20\x20\x20\x20\x20\x20\x20\x20\x20\x20\x20\x20\x20\x20\x20\x20\x20\x20\x20\x0a\x20\x20\x20\x20\x20\x20\x20\x20\x20\x20\x20\x20\x20\x20\x20\x20\x20\x20\x20\x20\x0a\x20\x20\x20\x20\x20\x20\x20\x20\x20\x20\x20\x20\x20\x20\x20\x20\x20\x20\x20\x20\x0a\x20\x20\x20\x20\x20\x20\x20\x20\x20\x20\x20\x20\x20\x20\x20\x20\x20\x20\x20\x20\x0a\x20\x20\x20\x20\x20\x20\x20\x20\x20\x20\x20\x20\x20\x20\x20\x20\x20\x20\x20\x20\x0a\x20\x20\x20\x20\x20\x20\x20\x20\x20\x20\x20\x20\x20\x20\x20\x20\x20\x20\x20\x20\x0a\x20\x20\x20\x20\x20\x20\x20\x20\x20\x20\x20\x20\x20\x20\x20\x20\x20\x20\x20\x20\x0a\x20\x20\x20\x20\x20\x20\x20\x20\x20\x20\x20\x20\x20\x20\x20\x20\x20\x20\x20\x20\x0a\x20\x20\x20\x20\x20\x20\x20\x20\x20\x20\x20\x20\x20\x20\x20\x20\x20\x20\x20\x20\x0a\x20\x20\x20\x20\x20\x20\x20\x20\x20\x20\x20\x20\x20\x20\x20\x20\x20\x20\x20\x20\x0a\x20\x20\x20\x20\x20\x20\x20\x20\x20\x20\x20\x20\x20\x20\x20\x20\x20\x20\x20\x20\x0a\x20\x20\x20\x20\x20\x20\x20\x20\x20\x20\x20\x20\x20\x20\x20\x20\x20\x20\x20\x20\x0a\x20\x20\x20\x20\x20\x20\x20\x20\x20\x20\x20\x20\x20\x20\x20\x20\x20\x20\x20\x20\x0a\x20\x20\x20\x20\x20\x20\x20\x20\x20\x20\x20\x20\x20\x20\x20\x20\x20\x20\x20\x20\x0a\x20\x20\x20\x20\x20\x20\x20\x20\x20\x20\x20\x20\x20\x20\x20\x20\x20\x20\x20\x20\x0a\x20\x20\x20\x20\x20\x20\x20\x20\x20\x20\x20\x20\x20\x20\x20\x20\x20\x20\x20\x20\x0a\x20\x20\x20\x20\x20\x20\x20\x20\x20\x20\x20\x20\x20\x20\x20\x20\x20\x20\x20\x20\x0a\x20\x20\x20\x20\x20\x20\x20\x20\x20\x20\x20\x20\x20\x20\x20\x20\x20\x20\x20\x20\x0a\x20\x20\x20\x20\x20\x20\x20\x20\x20\x20\x20\x3a\x20\x20\x20\x20\x20\x20\x20\x20\x0a\x20\x20\x20\x20\x20\x20\x20\x20\x20\x20\x20\x20\x20\x20\x20\x20\x20\x20\x20\x20\x0a\x20\x20\x71\x20\x20\x20\x20\x20\x20\x20\x20\x20\x20\x20\x20\x20\x20\x20\x20\x20\x0a\x20\x20\x20\x20\x20\x20\x20\x20\x20\x20\x20\x20\x20\x20\x20\x20\x20\x20\x20\x20\x0a\x20\x20\x20\x20\x20\x20\x20\x20\x20\x20\x20\x20\x20\x20\x20\x20\x20\x20\x20\x20\x0a\x20\x20\x20\x20\x20\x20\x20\x20\x20\x20\x20\x20\x20\x20\x20\x20\x20\x20\x20\x20\x0a\x20\x20\x20\x20\x20\x20\x20\x20\x20\x20\x20\x20\x20\x20\x20\x20\x20\x20\x20\x20\x0a\x20\x20\x20\x20\x20\x5c\x20\x20\x20\x20\x20\x20\x20\x20\x20\x20\x20\x20\x20\x20\x0a\x20\x20\x20\x20\x20\x20\x20\x20\x20\x20\x20\x20\x20\x20\x20\x20\x20\x20\x20\x20\x0a\x20\x20\x20\x20\x20\x20\x20\x20\x20\x20\x20\x20\x20\x20\x20\x20\x20\x20\x20\x20\x0a\x20\x20\x20\x20\x20\x20\x20\x20\x20\x20\x20\x20\x20\x20\x20\x20\x20\x20\x20\x20\x0a\x20\x20\x28\x2e\x20\x20\x20\x20\x20\x20\x20\x20\x20\x20\x20\x20\x20\x20\x20\x20\x0a\x20\x20\x20\x20\x20\x20\x20\x20\x20\x20\x20\x20\x20\x20\x20\x20\x20\x20\x20\x20\n</delim><match><data>\x20\x20\x20\x20\x20\x20\x20\x20\x20\x20\x20\x20\x20\x20\x20\x20\x20\x20\x20\x20\x0a\x20\x20\x20\x20\x20\x20\x20\x20\x20\x20\x20\x20\x20\x20\x20\x20\x20\x20\x20\x20\x0a\x20\x20\x20\x20\x20\x20\x20\x20\x20\x20\x20\x20\x20\x20\x20\x20\x20\x20\x20\x20\x0a\x20\x20\x20\x20\x20\x20\x20\x20\x20\x20\x20\x20\x20\x20\x20\x20\x20\x20\x20\x20\x0a\x20\x20\x20\x20\x20\x20\x20\x20\x20\x20\x20\x20\x20\x20\x20\x20\x20\x20\x20\x20\x0a\x20\x20\x20\x20\x20\x20\x20\x20\x20\x20\x20\x20\x20\x20\x20\x20\x20\x20\x20\x20\x0a\x20\x20\x20\x20\x20\x20\x20\x20\x20\x20\x20\x20\x20\x20\x20\x20\x20\x20\x20\x20\x0a\x20\x20\x20\x20\x20\x20\x20\x20\x20\x20\x20\x20\x20\x20\x20\x20\x20\x20\x20\x20\x0a\x20\x20\x20\x20\x20\x20\x20\x20\x20\x20\x20\x20\x20\x20\x20\x20\x20\x20\x20\x20\x0a\x20\x20\x20\x20\x20\x20\x20\x20\x20\x20\x20\x20\x20\x20\x20\x20\x20\x20\x20\x20\x0a\x20\x20\x20\x20\x20\x20\x20\x20\x20\x20\x20\x20\x20\x20\x20\x20\x20\x20\x20\x20\x0a\x20\x20\x20\x20\x20\x20\x20\x20\x20\x20\x20\x20\x20\x20\x20\x20\x20\x20\x20\x20\x0a\x20\x20\x20\x20\x20\x20\x20\x20\x20\x20\x20\x20\x20\x20\x20\x20\x20\x20\x20\x20\x0a\x20\x20\x20\x20\x20\x20\x20\x20\x20\x20\x20\x20\x20\x20\x20\x20\x20\x20\x20\x20\x0a\x20\x20\x20\x20\x20\x20\x20\x20\x20\x20\x20\x20\x20\x20\x20\x20\x20\x20\x20\x20\x0a\x20\x20\x20\x20\x20\x20\x20\x20\x20\x20\x20\x20\x20\x20\x20\x20\x20\x20\x20\x20\x0a\x20\x20\x20\x20\x20\x20\x20\x20\x20\x20\x20\x20\x20\x20\x20\x20\x20\x20\x20\x20\x0a\x20\x20\x20\x20\x20\x20\x20\x20\x20\x20\x20\x20\x20\x20\x20\x20\x20\x20\x20\x20\x0a\x20\x20\x20\x20\x20\x20\x20\x20\x20\x20\x20\x20\x20\x20\x20\x20\x20\x20\x20\x20\x0a\x20\x20\x20\x20\x20\x20\x20\x20\x20\x20\x20\x20\x20\x20\x20\x20\x20\x20\x20\x20\x0a\x20\x20\x20\x20\x20\x20\x20\x20\x20\x20\x20\x20\x20\x20\x20\x20\x20\x20\x20\x20\x0a\x20\x20\x20\x20\x20\x20\x20\x20\x20\x20\x20\x20\x20\x20\x20\x20\x20\x20\x20\x20\x0a\x20\x20\x20\x20\x20\x20\x20\x20\x20\x20\x20\x3a\x20\x20\x20\x20\x20\x20\x20\x20\x0a\x20\x20\x20\x20\x20\x20\x20\x20\x20\x20\x20\x20\x20\x20\x20\x20\x20\x20\x20\x20\x0a\x20\x20\x71\x20\x20\x20\x20\x20\x20\x20\x20\x20\x20\x20\x20\x20\x20\x20\x20\x20\x0a\x20\x20\x20\x20\x20\x20\x20\x20\x20\x20\x20\x20\x20\x20\x20\x20\x20\x20\x20\x20\x0a\x20\x20\x20\x20\x20\x20\x20\x20\x20\x20\x20\x20\x20\x20\x20\x20\x20\x20\x20\x20\x0a\x20\x20\x20\x20\x20\x20\x20\x20\x20\x20\x20\x20\x20\x20\x20\x20\x20\x20\x20\x20\x0a\x20\x20\x20\x20\x20\x20\x20\x20\x20\x20\x20\x20\x20\x20\x20\x20\x20\x20\x20\x20\x0a\x20\x20\x20\x20\x20\x5c\x20\x20\x20\x20\x20\x20\x20\x20\x20\x20\x20\x20\x20\x20\x0a\x20\x20\x20\x20\x20\x20\x20\x20\x20\x20\x20\x20\x20\x20\x20\x20\x20\x20\x20\x20\x0a\x20\x20\x20\x20\x20\x20\x20\x20\x20\x20\x20\x20\x20\x20\x20\x20\x20\x20\x20\x20\x0a\x20\x20\x20\x20\x20\x20\x20\x20\x20\x20\x20\x20\x20\x20\x20\x20\x20\x20\x20\x20\x0a\x20\x20\x28\x2e\x20\x20\x20\x20\x20\x20\x20\x20\x20\x20\x20\x20\x20\x20\x20\x20\x0a\x20\x20\x20\x20\x20\x20\x20\x20\x20\x20\x20\x20\x20\x20\x20\x20\x20\x20\x20\x20\n</data></match></read>
		<read echo="ascii"><delim>} </delim><match><data>1- Upload Image\n2- List Images\n3- Remove Image\n4- Display Image\n5- Leave\n} </data></match></read>
		<write echo="ascii"><data>5\n</data></write>
	</replay>
</pov>
